{"stats": {"num_bins": 100, "num_gateways": 4, "pdr": 99.17, "blindness": 3, "collision": 2}, "logs": ["Sim\u00fclasyon ba\u015flat\u0131l\u0131yor (Mod: Tam Analiz)...", "100 adet ak\u0131ll\u0131 \u00e7\u00f6p kutusu 5000m\u00b2 alana yerle\u015ftiriliyor...", "4 Gateway i\u00e7in sinyal yay\u0131l\u0131m ve g\u00f6lgeleme modelleri hesaplan\u0131yor...", "ADR Optimizasyonu: Sinyal kalitesine g\u00f6re SF atamalar\u0131 yap\u0131l\u0131yor...", "30 dakikal\u0131k trafik \u00f6r\u00fcnt\u00fcs\u00fc olu\u015fturuluyor (5 dakikal\u0131k aral\u0131klarla)...", "Paket \u00e7ak\u0131\u015fmalar\u0131 ve Gateway k\u00f6rl\u00fc\u011f\u00fc (Half-Duplex) analiz ediliyor...", "Mekansal da\u011f\u0131l\u0131m haritas\u0131 olu\u015fturuluyor...", "Kapsama Is\u0131 Haritas\u0131 (Heatmap) \u00fcretiliyor...", "B\u00f6lgesel verimlilik ve mahalle analizi yap\u0131l\u0131yor...", "Sinyal kalitesi ve enerji t\u00fcketimi grafikleri \u00fcretiliyor...", "Tam Analiz Modu: Stres testleri ve teorik limitler i\u015fleniyor...", "T\u00fcm sim\u00fclasyon ad\u0131mlar\u0131 ba\u015far\u0131yla tamamland\u0131."]}